screw_thread_lib/__init__.py
screw_thread_lib/threads.py
screw_thread_lib/data/ASME.py
screw_thread_lib/data/__init__.py
screw_thread_lib-0.0.6.dist-info/LICENSE
screw_thread_lib-0.0.6.dist-info/METADATA
screw_thread_lib-0.0.6.dist-info/WHEEL
screw_thread_lib-0.0.6.dist-info/top_level.txt
screw_thread_lib-0.0.6.dist-info/RECORD
