Metadata-Version: 2.1
Name: screw_thread_lib
Version: 0.0.6
Summary: A package for computing the strength of threaded fastener assemblies.
Home-page: https://github.com/denavit/ScrewThreadLib
Author: Mark Denavit
Author-email: mdenavit@utk.edu
License: MIT
Requires-Python: >=3.7
License-File: LICENSE
